ecatdump/__init__.py
ecatdump/cli.py
ecatdump/ecat_dump.py
ecatdump/helper_functions.py
ecatdump-0.2.6.dist-info/METADATA
ecatdump-0.2.6.dist-info/WHEEL
ecatdump-0.2.6.dist-info/entry_points.txt
ecatdump-0.2.6.dist-info/top_level.txt
ecatdump-0.2.6.dist-info/RECORD
